datamaps/__init__.py
datamaps/main.py
datamaps/api/__init__.py
datamaps/api/api.py
datamaps/core/__init__.py
datamaps/core/row.py
datamaps/core/temporal.py
datamaps/plugins/__init__.py
datamaps/plugins/dft/__init__.py
datamaps/plugins/dft/master.py
datamaps/plugins/dft/portfolio.py
datamaps/process/__init__.py
datamaps/process/cell.py
datamaps/process/cleansers.py
datamaps/tests/__init__.py
datamaps/tests/conftest.py
datamaps/tests/test_api.py
datamaps/tests/test_cleanser.py
datamaps/tests/test_cli.py
datamaps/tests/test_month.py
datamaps/tests/test_quarter.py
datamaps-1.1.9.dist-info/LICENSE.txt
datamaps-1.1.9.dist-info/METADATA
datamaps-1.1.9.dist-info/WHEEL
datamaps-1.1.9.dist-info/entry_points.txt
datamaps-1.1.9.dist-info/top_level.txt
datamaps-1.1.9.dist-info/RECORD
