Metadata-Version: 2.1
Name: datamaps
Version: 1.1.9
Summary: Collect and clean data using Excel spreadsheets.
Home-page: https://github.com/hammerheadlemon/datamaps
Author: Matthew Lemon
Author-email: matt@matthewlemon.com
Maintainer: Matthew Lemon
Maintainer-email: matt@matthewlemon.com
Keywords: data console commandline excel
Classifier: Development Status :: 3 - Alpha
Classifier: Environment :: Console
Classifier: Intended Audience :: Other Audience
Classifier: Programming Language :: Python :: 3.7
Classifier: Programming Language :: Python :: 3.8
Classifier: Programming Language :: Python :: 3.9
Classifier: Topic :: Text Processing
Requires-Python: >=3.6
License-File: LICENSE.txt
Requires-Dist: click
Requires-Dist: python-dateutil
Requires-Dist: bcompiler-engine (>=1.1.5)
